{
    "slogan": null,
    "sectionTitle": "Planet Xamarin",
    "socials": {
        "sessionize": null,
        "youtube": null,
        "mastodon": null,
        "twitter": "RTSchroeder",
        "linkedin": null,
        "github": "robintschroeder"
    },
    "tags": null,
    "bio": "Xamarin.Forms/UWP Software Consultant at MSCTek",
    "type": "CREATOR",
    "name": "Robin Schroeder",
    "feeds": [
        {
            "type": "AHrefFeedType",
            "url": "https://www.msctek.com/feed/"
        }
    ],
    "countryCode": "us",
    "channels": [
        {
            "url": "https://msctek.com/",
            "name": "Site"
        }
    ]
}
