{
  "name": "Microsoft Visual Studio",
  "sectionTitle": "👔 Official MSFT / .NET Foundation Content Resources / Xamarin",
  "countryCode": null,
  "slogan": "",
  "type": "OTHER",
  "bio": "",
  "tags": ".NET, Visual Studio",
  "socials": {
    "youtube": "https://www.youtube.com/c/visualstudio",
    "linkedin": "",
    "twitter": "",
    "github": "",
    "mastodon": "",
    "sessionize": ""
  },
  "channels": [
    {
      "name": "Blog",
      "url": "https://devblogs.microsoft.com/visualstudio/"
    }
  ],
  "feeds": [
    {
      "type": "LinkTagRssType",
      "url": "https://www.youtube.com/feeds/videos.xml?channel_id=UChqrDOwARrxdJF-ykAptc7w"
    },
    {
      "type": "LinkTagRssType",
      "url": "https://devblogs.microsoft.com/visualstudio/feed/"
    },
    {
      "type": "LinkTagRssType",
      "url": "https://devblogs.microsoft.com/visualstudio/comments/feed/"
    }
  ]
}