{
  "name": "Chris Sainty",
  "sectionTitle": null,
  "countryCode": "gb",
  "slogan": "",
  "type": "CREATOR",
  "bio": "",
  "tags": "Blazor",
  "socials": {
    "youtube": "",
    "linkedin": "",
    "twitter": "https://twitter.com/chris_sainty",
    "github": "",
    "mastodon": "https://mstdn.social/@chrissainty",
    "sessionize": ""
  },
  "channels": [
    {
      "name": "Blog",
      "url": "https://chrissainty.com/"
    },
    {
      "name": "Blazor in Action (Book)",
      "url": "https://bit.ly/blazorinaction"
    }
  ],
  "feeds": [
    {
      "type": "LinkTagRssType",
      "url": "https://chrissainty.com/rss/"
    }
  ]
}