{
  "name": "Jon Skeet",
  "sectionTitle": null,
  "countryCode": "gb",
  "slogan": "",
  "type": "CREATOR",
  "bio": "",
  "tags": ".NET, C#",
  "socials": {
    "youtube": "",
    "linkedin": "",
    "twitter": "https://twitter.com/jonskeet",
    "github": "https://github.com/jskeet/",
    "mastodon": "",
    "sessionize": ""
  },
  "channels": [
    {
      "name": "Blog",
      "url": "https://codeblog.jonskeet.uk/"
    },
    {
      "name": "Book",
      "url": "https://csharpindepth.com/"
    },
    {
      "name": "StackOverflow",
      "url": "https://stackoverflow.com/users/22656/jon-skeet"
    }
  ],
  "feeds": [
    {
      "type": "LinkTagRssType",
      "url": "https://codeblog.jonskeet.uk/feed/"
    }
  ]
}